semantic_core_kit/__init__.py
semantic_core_kit/ai_processor.py
semantic_core_kit/loader.py
semantic_core_kit/main.py
semantic_core_kit/utils.py
semantic_core_kit-0.1.0.dist-info/METADATA
semantic_core_kit-0.1.0.dist-info/WHEEL
semantic_core_kit-0.1.0.dist-info/top_level.txt
semantic_core_kit-0.1.0.dist-info/RECORD
