Metadata-Version: 2.4
Name: semantic_core_kit
Version: 0.1.0
Summary: AI-Assisted Semantic Core & Article Idea Generator
Author-email: Ihor Tykhonenko <tykhonenkoigor@gmail.com>
Keywords: seo,nlp,ai,keyword research,content generation,llm
Classifier: Programming Language :: Python :: 3
Classifier: License :: OSI Approved :: MIT License
Classifier: Operating System :: OS Independent
Classifier: Development Status :: 3 - Alpha
Classifier: Intended Audience :: Developers
Classifier: Topic :: Scientific/Engineering :: Artificial Intelligence
Classifier: Topic :: Software Development :: Libraries :: Python Modules
Classifier: Topic :: Text Processing :: Linguistic
Requires-Python: >=3.8
Requires-Dist: openai>=1.0.0
